llama_index/llms/cleanlab/__init__.py
llama_index/llms/cleanlab/base.py
llama_index_llms_cleanlab-0.6.1.dist-info/METADATA
llama_index_llms_cleanlab-0.6.1.dist-info/WHEEL
llama_index_llms_cleanlab-0.6.1.dist-info/licenses/LICENSE
llama_index_llms_cleanlab-0.6.1.dist-info/RECORD
