Metadata-Version: 2.4
Name: llama-index-llms-cleanlab
Version: 0.6.1
Summary: llama-index llms cleanlab integration
Author-email: Ashish Sardana <ashishsardana21@gmail.com>
License-Expression: MIT
License-File: LICENSE
Requires-Python: <4.0,>=3.9
Requires-Dist: cleanlab-tlm<2,>=1.1.2
Requires-Dist: llama-index-core<0.15,>=0.13.0
